{
  "family": "xgboost_v3",
  "stage": "deepen",
  "feature_lane": "baseline_three_only",
  "description": "Deepen iter1: wrap target with log1p (expm1 inverse). xgboost_v2 found this tie-positive (-322); test if it ports under feature-starved 3-feature regime.",
  "params_summary": "deepen_iter1_log1p_target",
  "seed": 42,
  "run_id": "20260507-212215-deepen-baseline_three_only",
  "experiment_source": "experiments\\xgboost_v3\\current_experiment.py",
  "created_at": "20260507-212215",
  "change_kind": "target",
  "hypothesis_unit": "log1p_target",
  "feature_group": "target_transform",
  "anchor_run_id": "20260507-211730-smoke-baseline_three_only"
}
